{"20210618032504000000":{"producto":"2","id":"2","nombre":"Juan","comentario":"aaaaaaaaaaa","email":"hola@email","fecha":"18-06-2021 03:25:04"},"20210809114408000000":{"id":"20210809114408000000","nombre":"Mariano","comentario":"Son de buenas calidad","producto":"10","email":"mariano.ghislanzoni@gmail.com","fecha":"09-08-2021 23:44:08"},"20210810014357000000":{"id":"20210810014357000000","nombre":"Mariano","comentario":"Hola mundo","producto":"10","email":"mghislanzoni@grupo-gestion.com.ar","fecha":"10-08-2021 01:43:57"}}